db_schemachange-1.1.1.dist-info/licenses/LICENSE
schemachange/__init__.py
schemachange/cli.py
schemachange/action/__init__.py
schemachange/action/deploy.py
schemachange/action/render.py
schemachange/action/rollback.py
schemachange/common/__init__.py
schemachange/common/schema.py
schemachange/common/utils.py
schemachange/config/__init__.py
schemachange/config/base.py
schemachange/config/change_history_table.py
schemachange/config/deploy_config.py
schemachange/config/get_merged_config.py
schemachange/config/parse_cli_args.py
schemachange/config/redact_config_secrets.py
schemachange/config/render_config.py
schemachange/config/rollback_config.py
schemachange/jinja/__init__.py
schemachange/jinja/jinja_env_var.py
schemachange/jinja/jinja_template_processor.py
schemachange/session/__init__.py
schemachange/session/base.py
schemachange/session/databricks_session.py
schemachange/session/mysql_session.py
schemachange/session/oracle_session.py
schemachange/session/postgres_session.py
schemachange/session/script.py
schemachange/session/session_factory.py
schemachange/session/snowflake_session.py
schemachange/session/sqlserver_session.py
db_schemachange-1.1.1.dist-info/METADATA
db_schemachange-1.1.1.dist-info/WHEEL
db_schemachange-1.1.1.dist-info/entry_points.txt
db_schemachange-1.1.1.dist-info/top_level.txt
db_schemachange-1.1.1.dist-info/RECORD
