Metadata-Version: 2.4
Name: db-schemachange
Version: 1.1.1
Summary: A simple, lightweight Python-based Database Change Management tool for various databases
Home-page: https://github.com/LTranData/db-schemachange
Author: LTranData
License: Apache-2.0
Classifier: License :: OSI Approved :: Apache Software License
Classifier: Operating System :: OS Independent
Classifier: Programming Language :: Python :: 3
Classifier: Programming Language :: Python :: 3 :: Only
Requires-Python: >=3.8
License-File: LICENSE
Requires-Dist: Jinja2==3.1.6
Requires-Dist: PyYAML==6.0.2
Requires-Dist: structlog==25.4.0
Requires-Dist: marshmallow==4.0.0
Requires-Dist: sqlparse==0.5.3
Requires-Dist: pyarrow==18.1.0
Provides-Extra: dev
Requires-Dist: black; extra == "dev"
Requires-Dist: flake8; extra == "dev"
Requires-Dist: pre-commit; extra == "dev"
Requires-Dist: pytest==8.4.1; extra == "dev"
Requires-Dist: pytest-cov==6.2.1; extra == "dev"
Provides-Extra: postgres
Requires-Dist: psycopg==3.2.9; extra == "postgres"
Requires-Dist: psycopg[binary]==3.2.9; extra == "postgres"
Provides-Extra: sqlserver
Requires-Dist: pymssql==2.3.6; extra == "sqlserver"
Provides-Extra: mysql
Requires-Dist: mysql-connector-python==9.3.0; extra == "mysql"
Provides-Extra: oracle
Requires-Dist: oracledb==3.2.0; extra == "oracle"
Provides-Extra: snowflake
Requires-Dist: snowflake-connector-python==3.16.0; extra == "snowflake"
Provides-Extra: databricks
Requires-Dist: databricks-sql-connector==4.0.5; extra == "databricks"
Requires-Dist: databricks-sdk==0.57.0; extra == "databricks"
Provides-Extra: all
Requires-Dist: psycopg==3.2.9; extra == "all"
Requires-Dist: psycopg[binary]==3.2.9; extra == "all"
Requires-Dist: pymssql==2.3.6; extra == "all"
Requires-Dist: mysql-connector-python==9.3.0; extra == "all"
Requires-Dist: oracledb==3.2.0; extra == "all"
Requires-Dist: snowflake-connector-python==3.16.0; extra == "all"
Requires-Dist: databricks-sql-connector==4.0.5; extra == "all"
Requires-Dist: databricks-sdk==0.57.0; extra == "all"
Dynamic: license-file
